odoo8_addon_mrp_production_estimated_cost-8.0.1.2.1-py2.7-nspkg.pth
odoo8_addon_mrp_production_estimated_cost-8.0.1.2.1.dist-info/DESCRIPTION.rst
odoo8_addon_mrp_production_estimated_cost-8.0.1.2.1.dist-info/METADATA
odoo8_addon_mrp_production_estimated_cost-8.0.1.2.1.dist-info/RECORD
odoo8_addon_mrp_production_estimated_cost-8.0.1.2.1.dist-info/WHEEL
odoo8_addon_mrp_production_estimated_cost-8.0.1.2.1.dist-info/metadata.json
odoo8_addon_mrp_production_estimated_cost-8.0.1.2.1.dist-info/namespace_packages.txt
odoo8_addon_mrp_production_estimated_cost-8.0.1.2.1.dist-info/top_level.txt
odoo_addons/mrp_production_estimated_cost/README.rst
odoo_addons/mrp_production_estimated_cost/__init__.py
odoo_addons/mrp_production_estimated_cost/__openerp__.py
odoo_addons/mrp_production_estimated_cost/data/analytic_journal_data.xml
odoo_addons/mrp_production_estimated_cost/data/virtual_mrp_production_sequence.xml
odoo_addons/mrp_production_estimated_cost/i18n/am.po
odoo_addons/mrp_production_estimated_cost/i18n/ar.po
odoo_addons/mrp_production_estimated_cost/i18n/bg.po
odoo_addons/mrp_production_estimated_cost/i18n/bs.po
odoo_addons/mrp_production_estimated_cost/i18n/ca.po
odoo_addons/mrp_production_estimated_cost/i18n/ca_ES.po
odoo_addons/mrp_production_estimated_cost/i18n/cs.po
odoo_addons/mrp_production_estimated_cost/i18n/da.po
odoo_addons/mrp_production_estimated_cost/i18n/de.po
odoo_addons/mrp_production_estimated_cost/i18n/el_GR.po
odoo_addons/mrp_production_estimated_cost/i18n/en_AU.po
odoo_addons/mrp_production_estimated_cost/i18n/en_GB.po
odoo_addons/mrp_production_estimated_cost/i18n/es.po
odoo_addons/mrp_production_estimated_cost/i18n/es_AR.po
odoo_addons/mrp_production_estimated_cost/i18n/es_CL.po
odoo_addons/mrp_production_estimated_cost/i18n/es_CO.po
odoo_addons/mrp_production_estimated_cost/i18n/es_CR.po
odoo_addons/mrp_production_estimated_cost/i18n/es_DO.po
odoo_addons/mrp_production_estimated_cost/i18n/es_EC.po
odoo_addons/mrp_production_estimated_cost/i18n/es_ES.po
odoo_addons/mrp_production_estimated_cost/i18n/es_MX.po
odoo_addons/mrp_production_estimated_cost/i18n/es_PE.po
odoo_addons/mrp_production_estimated_cost/i18n/es_PY.po
odoo_addons/mrp_production_estimated_cost/i18n/es_VE.po
odoo_addons/mrp_production_estimated_cost/i18n/et.po
odoo_addons/mrp_production_estimated_cost/i18n/eu.po
odoo_addons/mrp_production_estimated_cost/i18n/fa.po
odoo_addons/mrp_production_estimated_cost/i18n/fi.po
