Metadata-Version: 2.0
Name: odoo8-addon-mrp-production-estimated-cost
Version: 8.0.1.2.1
Summary: Estimated costs in manufacturing orders
Home-page: http://www.odoomrp.com
Author: OdooMRP team, AvanzOSC, Serv. Tecnol. Avanzados - Pedro M. Baeza, Antiun Ingenería S.L.,Odoo Community Association (OCA)
Author-email: support@odoo-community.org
License: AGPL-3
Platform: UNKNOWN
Classifier: Programming Language :: Python :: 2.7
Classifier: Framework :: Odoo
Classifier: License :: OSI Approved :: GNU Affero General Public License v3
Requires-Dist: odoo (<9.0a,>=8.0a)
Requires-Dist: odoo8-addon-mrp-operations-project
